aleksis/apps/plank/__init__.py
aleksis/apps/plank/admin.py
aleksis/apps/plank/apps.py
aleksis/apps/plank/forms.py
aleksis/apps/plank/frontend/components/AttributesTable.vue
aleksis/apps/plank/frontend/components/DeleteDialog.vue
aleksis/apps/plank/frontend/components/DetailPage.vue
aleksis/apps/plank/frontend/components/FormDialog.vue
aleksis/apps/plank/frontend/components/ItemList.vue
aleksis/apps/plank/frontend/components/attributeRows/AttributeRow.vue
aleksis/apps/plank/frontend/components/attributeRows/BarcodeRow.vue
aleksis/apps/plank/frontend/components/attributeRows/BorrowingPersonRow.vue
aleksis/apps/plank/frontend/components/attributeRows/CategoryRow.vue
aleksis/apps/plank/frontend/components/attributeRows/CheckInUntilRow.vue
aleksis/apps/plank/frontend/components/attributeRows/CheckOutConditionRow.vue
aleksis/apps/plank/frontend/components/attributeRows/CheckOutProcessStatusRow.vue
aleksis/apps/plank/frontend/components/attributeRows/CheckedOutAtRow.vue
aleksis/apps/plank/frontend/components/attributeRows/DescriptionRow.vue
aleksis/apps/plank/frontend/components/attributeRows/InventoryRow.vue
aleksis/apps/plank/frontend/components/attributeRows/ItemStatusRow.vue
aleksis/apps/plank/frontend/components/attributeRows/ItemTypeRow.vue
aleksis/apps/plank/frontend/components/attributeRows/LastTimeSeenAtRow.vue
aleksis/apps/plank/frontend/components/attributeRows/LendingPersonRow.vue
aleksis/apps/plank/frontend/components/attributeRows/LocationRow.vue
aleksis/apps/plank/frontend/components/attributeRows/ManufacturerRow.vue
aleksis/apps/plank/frontend/components/attributeRows/NotesRow.vue
aleksis/apps/plank/frontend/components/attributeRows/ParentLocationsRow.vue
aleksis/apps/plank/frontend/components/attributeRows/PartNumberRow.vue
aleksis/apps/plank/frontend/components/attributeRows/PersonRow.vue
aleksis/apps/plank/frontend/components/attributeRows/SerialNumberRow.vue
aleksis/apps/plank/frontend/components/category/CategoryBaseList.vue
aleksis_app_plank-0.1.dist-info/METADATA
aleksis_app_plank-0.1.dist-info/WHEEL
aleksis_app_plank-0.1.dist-info/entry_points.txt
aleksis_app_plank-0.1.dist-info/RECORD
