Metadata-Version: 2.1
Name: aleksis-app-plank
Version: 0.1
Summary: AlekSIS (School Information System) — App Plank
Home-page: https://aleksis.org
License: EUPL-1.2-or-later
Author: Jonathan Weth
Author-email: dev@jonathanweth.de
Maintainer: Jonathan Weth
Maintainer-email: dev@jonathanweth.de
Requires-Python: >=3.9,<4.0
Classifier: License :: Other/Proprietary License
Classifier: Programming Language :: Python :: 3
Classifier: Programming Language :: Python :: 3.9
Classifier: Programming Language :: Python :: 3.10
Classifier: Programming Language :: Python :: 3.11
Requires-Dist: aleksis-core (>=3.0,<4.0)
Project-URL: Repository, https://edugit.org/AlekSIS/onboarding/AlekSIS-App-Plank
